{
  "the_new_excerpt": "",
  "original_created_utc": 1616772543,
  "localize": [
    {
      "locale": "zh",
      "title": "𝗟𝗲𝗶𝘀𝘂𝗿𝗲𝗹𝘆 𝗯𝗼𝗮𝘁 𝘁𝗿𝗶𝗽 𝗼𝗻 𝘁𝗵𝗲 𝗦𝘂𝗲𝘇 𝗖𝗮𝗻𝗮𝗹? 为什么会有这样的关系！？可能会出现天然气和粮食危机。"
    },
    {
      "locale": "zh-Hant",
      "title": "𝗟𝗲𝗶𝘀𝘂𝗿𝗲𝗹𝘆 𝗯𝗼𝗮𝘁 𝘁𝗿𝗶𝗽 𝗼𝗻 𝘁𝗵𝗲 𝗦𝘂𝗲𝘇 𝗖𝗮𝗻𝗮𝗹? 爲什麼會有這樣的關係！？可能會出現天然氣和糧食危機。"
    }
  ],
  "title": "𝗟𝗲𝗶𝘀𝘂𝗿𝗲𝗹𝘆 𝗯𝗼𝗮𝘁 𝘁𝗿𝗶𝗽 𝗼𝗻 𝘁𝗵𝗲 𝗦𝘂𝗲𝘇 𝗖𝗮𝗻𝗮𝗹? Why is this relevant! There might be a gas and food crisis on the way.",
  "created_utc": 1616858863,
  "selftext_html": null,
  "score": 1105,
  "preview": {
    "images": [
      {
        "source": {
          "url": "https://preview.redd.it/ak13l21q4ep61.jpg?auto=webp&s=83173054c3af53d4293970ef043c99b08474298a",
          "width": 2362,
          "height": 2362
        },
        "resolutions": [
          {
            "url": "https://preview.redd.it/ak13l21q4ep61.jpg?width=108&crop=smart&auto=webp&s=b638187d2ba3a60c5f55f6f5ff467b50d4185be2",
            "width": 108,
            "height": 108
          },
          {
            "url": "https://preview.redd.it/ak13l21q4ep61.jpg?width=216&crop=smart&auto=webp&s=422771d4975e41d5153af0a50ac5fc6e1a031551",
            "width": 216,
            "height": 216
          },
          {
            "url": "https://preview.redd.it/ak13l21q4ep61.jpg?width=320&crop=smart&auto=webp&s=e5cd8248e383aada8bc7e7a49bd96f4e40bb7579",
            "width": 320,
            "height": 320
          },
          {
            "url": "https://preview.redd.it/ak13l21q4ep61.jpg?width=640&crop=smart&auto=webp&s=8c83bed803cee4c11cccde7486291582b468ca89",
            "width": 640,
            "height": 640
          },
          {
            "url": "https://preview.redd.it/ak13l21q4ep61.jpg?width=960&crop=smart&auto=webp&s=2dd13f42eb0a7548e25f20206eab2069c50d2473",
            "width": 960,
            "height": 960
          },
          {
            "url": "https://preview.redd.it/ak13l21q4ep61.jpg?width=1080&crop=smart&auto=webp&s=a1cf2427b80e746c35023a5bb2b6fbfd14e89925",
            "width": 1080,
            "height": 1080
          }
        ],
        "variants": {},
        "id": "PViwI69ytmw-TMyk7EVZGquoltwD_e5SX2wlaG9j5m4"
      }
    ],
    "enabled": true
  },
  "permalink": "/r/wallstreetbets/comments/mdr5a4/𝗟𝗲𝗶𝘀𝘂𝗿𝗲𝗹𝘆_𝗯𝗼𝗮𝘁_𝘁𝗿𝗶𝗽_𝗼𝗻_𝘁𝗵𝗲_𝗦𝘂𝗲𝘇_𝗖𝗮𝗻𝗮𝗹_why_is_this/",
  "subreddit": "wallstreetbets",
  "id": "mdr5a4",
  "is_self": false,
  "media": null,
  "is_video": false,
  "source_updated_at": 1617357147047
}