{
  "the_new_excerpt": "this has been happening too frequently and all I wanna do is see my\nmasterpiece😩( I don’t have a skat fetish or anything) I just wanna see my art",
  "original_created_utc": 1621805218,
  "localize": [
    {
      "locale": "ja",
      "the_new_excerpt": "これはあまりにも頻繁に起こっていることで、私がしたいのは自分の傑作を見ることです。\n傑作を見たい😩（スケートフェチでもなんでもない）私はただ自分の芸術を見たいのです",
      "title": "何かを得ようとした時、振り返るとそこには何もなかったという経験はありませんか？まるで存在しなかったかのように😳。"
    },
    {
      "locale": "zh",
      "the_new_excerpt": "这事发生得太频繁了，我只想看看我的\n(我没有滑板癖或任何东西) 我只想看到我的艺术。",
      "title": "有谁曾经在拉完屎后，一转身就不见了？几乎就像它从未存在过一样😳"
    },
    {
      "locale": "zh-Hant",
      "the_new_excerpt": "這事發生得太頻繁了，我只想看看我的\n(我沒有滑板癖或任何東西) 我只想看到我的藝術。",
      "title": "有誰曾經在拉完屎後，一轉身就不見了？幾乎就像它從未存在過一樣😳"
    }
  ],
  "title": "Anybody ever just a shit and then turn around and it’s not there? It’s almost like it never existed😳",
  "created_utc": 1621872170,
  "selftext_html": "<!-- SC_OFF --><div class=\"md\"><p>this has been happening too frequently and all I wanna do is see my masterpiece😩( I don’t have a skat fetish or anything) I just wanna see my art</p>\n</div><!-- SC_ON -->",
  "score": 103,
  "permalink": "/r/TooAfraidToAsk/comments/njhqrh/anybody_ever_just_a_shit_and_then_turn_around_and/",
  "subreddit": "TooAfraidToAsk",
  "id": "njhqrh",
  "is_self": true,
  "media": null,
  "is_video": false
}