{
  "the_new_excerpt": "",
  "original_created_utc": 1623686220,
  "localize": [
    {
      "locale": "ja",
      "title": "$WISH ✋🏾💎🤚🏾 YOLO see you at $25 💎✋🏾🦍🙏🏿💪🏿"
    },
    {
      "locale": "zh",
      "title": "$WISH ✋🏾💎🤚🏾YOLO在25美元处见到你💎✋🏾🦍🙏🏿💪🏿"
    },
    {
      "locale": "zh-Hant",
      "title": "$WISH ✋🏾💎🤚🏾YOLO在25美元處見到你💎✋🏾🦍🙏🏿💪🏿"
    }
  ],
  "title": "$WISH ✋🏾💎🤚🏾 YOLO see you at $25 💎✋🏾🦍🙏🏿💪🏿",
  "created_utc": 1623719935,
  "selftext_html": null,
  "score": 1189,
  "permalink": "/r/wallstreetbets/comments/nzq0yx/wish_yolo_see_you_at_25/",
  "subreddit": "wallstreetbets",
  "id": "nzq0yx",
  "is_self": false,
  "media": null,
  "is_video": false,
  "source_updated_at": 1624009747688
}