{
  "the_new_excerpt": "",
  "original_created_utc": 1619644244,
  "localize": [
    {
      "locale": "ja",
      "title": "アポロ11号のパイロット、マイケル・コリンズが本日、亡くなりました。バズ・オルドリンとニール・アームストロングが月面にいる間、彼は司令室で28時間、一人で月の周りを回っていました。マイケル・コリンズさんのご冥福をお祈りします。あなたは若い世代に宇宙産業への就職を勧め続けています。🚀"
    },
    {
      "locale": "zh",
      "title": "阿波罗11号飞行员迈克尔-柯林斯今天去世了。当巴斯-奥尔德林和尼尔-阿姆斯特朗在月球上时，他在指挥舱中独自绕月球28个小时。迈克尔-柯林斯安息，你继续激励年轻一代从事航天业的工作。🚀"
    },
    {
      "locale": "zh-Hant",
      "title": "阿波羅11號飛行員邁克爾-柯林斯今天去世了。當巴斯-奧爾德林和尼爾-阿姆斯特朗在月球上時，他在指揮艙中獨自繞月球28個小時。邁克爾-柯林斯安息，你繼續激勵年輕一代從事航天業的工作。🚀"
    }
  ],
  "title": "Apollo 11 Pilot, Michael Collins has passed away today. While Buzz Aldrin and Neil Armstrong were on the moon, he was in the Command Module orbiting the moon for 28 hours, alone. Rest In Peace Michael Collins, you continue to inspire the younger generation to pursue a job in the space industry. 🚀",
  "created_utc": 1619671675,
  "selftext_html": null,
  "score": 98411,
  "preview": {
    "images": [
      {
        "source": {
          "url": "https://preview.redd.it/50axygcdczv61.jpg?auto=webp&s=a0a553d820acab34f24a64af2e3cdf55eceeb727",
          "width": 1080,
          "height": 1356
        },
        "resolutions": [
          {
            "url": "https://preview.redd.it/50axygcdczv61.jpg?width=108&crop=smart&auto=webp&s=39a96ecc20ebba4208692fc19987b068bd233d42",
            "width": 108,
            "height": 135
          },
          {
            "url": "https://preview.redd.it/50axygcdczv61.jpg?width=216&crop=smart&auto=webp&s=8f13fc756fd21b4a56fd45df9614a1f2b37a72e5",
            "width": 216,
            "height": 271
          },
          {
            "url": "https://preview.redd.it/50axygcdczv61.jpg?width=320&crop=smart&auto=webp&s=80981cf1f35dd0cf977e9d996970e89f614e7c82",
            "width": 320,
            "height": 401
          },
          {
            "url": "https://preview.redd.it/50axygcdczv61.jpg?width=640&crop=smart&auto=webp&s=52d93394a866c2a5d652e9423f93c7faf75e8040",
            "width": 640,
            "height": 803
          },
          {
            "url": "https://preview.redd.it/50axygcdczv61.jpg?width=960&crop=smart&auto=webp&s=c52a8885fa60470ec25a68beae11a16620fc90db",
            "width": 960,
            "height": 1205
          },
          {
            "url": "https://preview.redd.it/50axygcdczv61.jpg?width=1080&crop=smart&auto=webp&s=37715e8b630682a32211d72c7075b98fa72b3f01",
            "width": 1080,
            "height": 1356
          }
        ],
        "variants": {},
        "id": "rHrY8V0-H-y5t-AzhvmhZyFGx9nJoYT4FKdHz8B8YBg"
      }
    ],
    "enabled": true
  },
  "permalink": "/r/interestingasfuck/comments/n0owwz/apollo_11_pilot_michael_collins_has_passed_away/",
  "subreddit": "interestingasfuck",
  "id": "n0owwz",
  "is_self": false,
  "media": null,
  "is_video": false,
  "source_updated_at": 1619776200358
}