{
  "the_new_excerpt": "Interesting dichotomy looking at APPLE in regards to the overall market. Last\nweek they re-opened all their stores. So you have to wonder what market forces\nor restraining apple share prices. The one unknown is warren Buffett. Is he\nstill bullish on Apple or did he decide to take his chips and move…",
  "original_created_utc": 1615227863,
  "localize": [
    {
      "locale": "zh",
      "the_new_excerpt": "从整体市场来看APPLE，有趣的二分法。最后\n周，他们重新开放了所有的店铺。所以你不得不怀疑是什么市场力量\n或制约苹果股价。一个未知的是巴菲特。他是\n还是看好苹果，还是他决定拿着他的筹码搬...",
      "title": "苹果公司的下一步行动"
    },
    {
      "locale": "zh-Hant",
      "the_new_excerpt": "從整體市場來看APPLE，有趣的二分法。最後\n周，他們重新開放了所有的店鋪。所以你不得不懷疑是什麼市場力量\n或制約蘋果股價。一個未知的是巴菲特。他是\n還是看好蘋果，還是他決定拿着他的籌碼搬...",
      "title": "蘋果公司的下一步行動"
    }
  ],
  "title": "Next step for Apple 🍎",
  "created_utc": 1615262063,
  "selftext_html": "<!-- SC_OFF --><div class=\"md\"><p>Interesting dichotomy looking at APPLE in regards to the overall market. Last week they re-opened all their stores. So you have to wonder what market forces or restraining apple share prices.\nThe one unknown is warren Buffett. Is he still bullish on Apple or did he decide to take his chips and move on. He has a tendency to do it and of course none of us would know until the next quarter when financial disclosures are released.</p>\n</div><!-- SC_ON -->",
  "score": 48,
  "permalink": "/r/stocks/comments/m0m8n4/next_step_for_apple/",
  "subreddit": "stocks",
  "id": "m0m8n4",
  "is_self": true,
  "media": null,
  "is_video": false,
  "source_updated_at": 1615542577953
}